xl_mcp_demo/__init__.py
xl_mcp_demo-0.1.0.dist-info/METADATA
xl_mcp_demo-0.1.0.dist-info/WHEEL
xl_mcp_demo-0.1.0.dist-info/entry_points.txt
xl_mcp_demo-0.1.0.dist-info/RECORD
